timeslime_rpi/__init__.py
timeslime_rpi/__main__.py
timeslime_rpi/handler.py
timeslime_rpi-1.3.5.dist-info/LICENSE
timeslime_rpi-1.3.5.dist-info/METADATA
timeslime_rpi-1.3.5.dist-info/WHEEL
timeslime_rpi-1.3.5.dist-info/entry_points.txt
timeslime_rpi-1.3.5.dist-info/top_level.txt
timeslime_rpi-1.3.5.dist-info/RECORD
