Metadata-Version: 2.1
Name: timeslime-rpi
Version: 1.3.5
Summary: UNKNOWN
Home-page: UNKNOWN
Author: Christian Decker
Author-email: christian.decker@lookslikematrix.de
License: MIT
Project-URL: Donate, https://www.buymeacoffee.com/lookslikematrix
Project-URL: Source Code, https://gitlab.com/lookslikematrix/timeslime-rpi
Platform: UNKNOWN
Classifier: Programming Language :: Python :: 3
Requires-Python: >=3.7
License-File: LICENSE
Requires-Dist: timeslime (==1.5.4)
Requires-Dist: gpiozero (==1.6.2)
Requires-Dist: rpi.gpio (==0.7.1)
Requires-Dist: rpi-tm1637 (==1.3.4)
